databricks_sql/__init__.py
databricks_sql/client.py
databricks_sql-1.0.0.dist-info/WHEEL
databricks_sql-1.0.0.dist-info/LICENSE
databricks_sql-1.0.0.dist-info/METADATA
databricks_sql-1.0.0.dist-info/RECORD
