Metadata-Version: 2.1
Name: databricks-sql
Version: 1.0.0
Summary: Databricks SQL framework, easy to learn, fast to code, ready for production.
Home-page: https://github.com/bernardocouto/databricks-sql
License: Apache 2-0
Author: Bernardo Couto
Author-email: bernardocouto@icloud.com
Requires-Python: >=3.8,<4.0
Classifier: License :: Other/Proprietary License
Classifier: Programming Language :: Python :: 3
Classifier: Programming Language :: Python :: 3.8
Classifier: Programming Language :: Python :: 3.9
Classifier: Programming Language :: Python :: 3.10
Classifier: Programming Language :: Python :: 3.11
Classifier: Programming Language :: Python :: 3
Classifier: Topic :: Database
Requires-Dist: databricks-sql-connector (==2.2.1)
Requires-Dist: pystache (==0.6.0)
Project-URL: Repository, https://github.com/bernardocouto/databricks-sql
